MANIFEST.in
README.rst
readme.rst
requirements.txt
setup.py
versionone_to_jira_reflector/__init__.py
versionone_to_jira_reflector/cmdline.py
versionone_to_jira_reflector/exceptions.py
versionone_to_jira_reflector/jira_client.py
versionone_to_jira_reflector/main.py
versionone_to_jira_reflector/util.py
versionone_to_jira_reflector.egg-info/PKG-INFO
versionone_to_jira_reflector.egg-info/SOURCES.txt
versionone_to_jira_reflector.egg-info/dependency_links.txt
versionone_to_jira_reflector.egg-info/entry_points.txt
versionone_to_jira_reflector.egg-info/pbr.json
versionone_to_jira_reflector.egg-info/requires.txt
versionone_to_jira_reflector.egg-info/top_level.txt