Metadata-Version: 1.1
Name: versionone-to-jira-reflector
Version: 0.5.6
Summary: Copy/update JIRA issues to match your VersionOne stories.
Home-page: https://github.com/coddingtonbear/versionone-to-jira-reflector
Author: Adam Coddington
Author-email: me@adamcoddington.net
License: UNKNOWN
Platform: UNKNOWN
Classifier: License :: OSI Approved :: MIT License
Classifier: Operating System :: OS Independent
Classifier: Programming Language :: Python :: 3
